polymodel/__init__.py
polymodel/_compat.py
polymodel/default.py
polymodel/ext/__init__.py
polymodel/ext/asyncio/__init__.py
polymodel/ext/asyncio/session.py
polymodel/main.py
polymodel/orm/__init__.py
polymodel/orm/session.py
polymodel/pool/__init__.py
polymodel/py.typed
polymodel/sql/__init__.py
polymodel/sql/_expression_select_cls.py
polymodel/sql/_expression_select_gen.py
polymodel/sql/_expression_select_gen.py.jinja2
polymodel/sql/base.py
polymodel/sql/expression.py
polymodel/sql/sqltypes.py
polymodel-0.0.1.dist-info/WHEEL
polymodel-0.0.1.dist-info/METADATA
polymodel-0.0.1.dist-info/RECORD
