Metadata-Version: 2.3
Name: polymodel
Version: 0.0.1
Summary: PolyModel, a modern, flexible ORM with full Pydantic compatibility
Author: Ramón Vila Ferreres
Author-email: Ramón Vila Ferreres <ramonvilafer@proton.me>
Classifier: Development Status :: 4 - Beta
Classifier: Framework :: AsyncIO
Classifier: Intended Audience :: Developers
Classifier: Intended Audience :: Science/Research
Classifier: Intended Audience :: System Administrators
Classifier: License :: OSI Approved :: MIT License
Classifier: Programming Language :: Python :: 3 :: Only
Classifier: Programming Language :: Python :: 3.8
Classifier: Programming Language :: Python :: 3.9
Classifier: Programming Language :: Python :: 3.10
Classifier: Programming Language :: Python :: 3.11
Classifier: Programming Language :: Python :: 3.12
Classifier: Programming Language :: Python :: 3.13
Classifier: Topic :: Database
Classifier: Topic :: Database :: Database Engines/Servers
Classifier: Topic :: Internet
Classifier: Topic :: Internet :: WWW/HTTP :: HTTP Servers
Classifier: Topic :: Internet :: WWW/HTTP
Classifier: Typing :: Typed
Requires-Dist: sqlalchemy>=2.0.14,<2.1.0
Requires-Dist: pydantic>=1.10.13,<3.0.0
Requires-Python: >=3.12
Project-URL: Homepage, https://github.com/rmonvfer/polymodel
Project-URL: Issues, https://github.com/rmonvfer/polymodel/issues
Project-URL: Source, https://github.com/rmonvfer/polymodel
Project-URL: Upstream, https://github.com/sqlmodel/sqlmodel
